<?xml version="1.0" encoding="UTF-8"?>
<export version="D">
  <design>
    <source>/home/pedro/kicad_projects/imac_g3_333mhz_slot_loading_J20_adapter_board/imac_g3_333mhz_slot_loading_J20_adapter_board.sch</source>
    <date>Mon 09 Mar 2020 03:44:55 PM EDT</date>
    <tool>Eeschema 5.1.5-52549c5~84~ubuntu18.04.1</tool>
    <sheet number="1" name="/" tstamps="/">
      <title_block>
        <title>iMac G3 333 Mhz Slot Loading Power and Video Board</title>
        <company/>
        <rev>1</rev>
        <date>2020-02-03</date>
        <source>imac_g3_333mhz_slot_loading_J20_adapter_board.sch</source>
        <comment number="1" value="and control other functions."/>
        <comment number="2" value="used to send the i2c IVAD inititialization sequence and the EDID info to the computer"/>
        <comment number="3" value="Powers atmega328p fromJ20 and powers an atmega328p from VGA cable"/>
        <comment number="4" value="Rocky Hill"/>
      </title_block>
    </sheet>
  </design>
  <components>
    <comp ref="U1">
      <value>ATmega328-PU</value>
      <footprint>Package_DIP:DIP-28_W7.62mm</footprint>
      <datasheet>http://ww1.microchip.com/downloads/en/DeviceDoc/ATmega328_P%20AVR%20MCU%20with%20picoPower%20Technology%20Data%20Sheet%2040001984A.pdf</datasheet>
      <libsource lib="MCU_Microchip_ATmega" part="ATmega328-PU" description="20MHz, 32kB Flash, 2kB SRAM, 1kB EEPROM, DIP-28"/>
      <sheetpath names="/" tstamps="/"/>
      <tstamp>5E393326</tstamp>
    </comp>
    <comp ref="Y1">
      <value>Crystal</value>
      <footprint>Crystal:Crystal_HC49-U_Vertical</footprint>
      <datasheet>http://www.txccrystal.com/images/pdf/9b.pdf</datasheet>
      <fields>
        <field name="Part#">887-2015-ND</field>
        <field name="Vendor">digikey</field>
      </fields>
      <libsource lib="Device" part="Crystal" description="Two pin crystal"/>
      <sheetpath names="/" tstamps="/"/>
      <tstamp>5E39C3FD</tstamp>
    </comp>
    <comp ref="C1">
      <value>22pF</value>
      <footprint>Capacitor_THT:C_Disc_D9.0mm_W5.0mm_P10.00mm</footprint>
      <datasheet>http://www.vishay.com/docs/28537/vy1series.pdf</datasheet>
      <fields>
        <field name="Part#">BC2364-ND</field>
        <field name="Vendor">digikey</field>
      </fields>
      <libsource lib="Device" part="C" description="Unpolarized capacitor"/>
      <sheetpath names="/" tstamps="/"/>
      <tstamp>5E39D342</tstamp>
    </comp>
    <comp ref="C2">
      <value>22pF</value>
      <footprint>Capacitor_THT:C_Disc_D9.0mm_W5.0mm_P10.00mm</footprint>
      <datasheet>http://www.vishay.com/docs/28537/vy1series.pdf</datasheet>
      <fields>
        <field name="Part#">BC2364-ND</field>
        <field name="Vendor">digikey</field>
      </fields>
      <libsource lib="Device" part="C" description="Unpolarized capacitor"/>
      <sheetpath names="/" tstamps="/"/>
      <tstamp>5E552ABD</tstamp>
    </comp>
    <comp ref="J20">
      <value>Conn_02x10_Odd_Even</value>
      <footprint>Connector_PinHeader_2.54mm:PinHeader_2x10_P2.54mm_Vertical</footprint>
      <datasheet>https://cdn.amphenol-icc.com/media/wysiwyg/files/drawing/67996.pdf</datasheet>
      <fields>
        <field name="Part#">609-3206-ND</field>
        <field name="Vendor">digikey</field>
      </fields>
      <libsource lib="Connector_Generic" part="Conn_02x10_Odd_Even" description="Generic connector, double row, 02x10, odd/even pin numbering scheme (row 1 odd numbers, row 2 even numbers), script generated (kicad-library-utils/schlib/autogen/connector/)"/>
      <sheetpath names="/" tstamps="/"/>
      <tstamp>5E3F686C</tstamp>
    </comp>
    <comp ref="J1">
      <value>DB15_Female_HighDensity</value>
      <footprint>Connector_Dsub:DSUB-15-HD_Female_Horizontal_P2.29x1.98mm_EdgePinOffset8.35mm_Housed_MountingHolesOffset10.89mm</footprint>
      <datasheet>https://cdn.amphenol-icc.com/media/wysiwyg/files/drawing/l77hdxxxsd1ch4f.pdf</datasheet>
      <fields>
        <field name="Part#">L77HDE15SD1CH4F-ND</field>
        <field name="Vendor">digikey</field>
      </fields>
      <libsource lib="Connector" part="DB15_Female_HighDensity" description="15-pin female D-SUB connector, High density (3 columns), Triple Row, Generic, VGA-connector"/>
      <sheetpath names="/" tstamps="/"/>
      <tstamp>5E3B898B</tstamp>
    </comp>
    <comp ref="Y2">
      <value>Crystal</value>
      <footprint>Crystal:Crystal_HC49-U_Vertical</footprint>
      <datasheet>http://www.txccrystal.com/images/pdf/9b.pdf</datasheet>
      <fields>
        <field name="Part#">887-2015-ND</field>
        <field name="Vendor">digikey</field>
      </fields>
      <libsource lib="Device" part="Crystal" description="Two pin crystal"/>
      <sheetpath names="/" tstamps="/"/>
      <tstamp>5E555ABD</tstamp>
    </comp>
    <comp ref="C4">
      <value>22pF</value>
      <footprint>Capacitor_THT:C_Disc_D9.0mm_W5.0mm_P10.00mm</footprint>
      <datasheet>http://www.vishay.com/docs/28537/vy1series.pdf</datasheet>
      <fields>
        <field name="Part#">BC2364-ND</field>
        <field name="Vendor">digikey</field>
      </fields>
      <libsource lib="Device" part="C" description="Unpolarized capacitor"/>
      <sheetpath names="/" tstamps="/"/>
      <tstamp>5E554B25</tstamp>
    </comp>
    <comp ref="C3">
      <value>22pF</value>
      <footprint>Capacitor_THT:C_Disc_D9.0mm_W5.0mm_P10.00mm</footprint>
      <datasheet>http://www.vishay.com/docs/28537/vy1series.pdf</datasheet>
      <fields>
        <field name="Part#">BC2364-ND</field>
        <field name="Vendor">digikey</field>
      </fields>
      <libsource lib="Device" part="C" description="Unpolarized capacitor"/>
      <sheetpath names="/" tstamps="/"/>
      <tstamp>5E552F81</tstamp>
    </comp>
    <comp ref="U2">
      <value>ATmega328-PU</value>
      <footprint>Package_DIP:DIP-28_W7.62mm</footprint>
      <datasheet>http://ww1.microchip.com/downloads/en/DeviceDoc/ATmega328_P%20AVR%20MCU%20with%20picoPower%20Technology%20Data%20Sheet%2040001984A.pdf</datasheet>
      <libsource lib="MCU_Microchip_ATmega" part="ATmega328-PU" description="20MHz, 32kB Flash, 2kB SRAM, 1kB EEPROM, DIP-28"/>
      <sheetpath names="/" tstamps="/"/>
      <tstamp>5E42FE47</tstamp>
    </comp>
    <comp ref="U3">
      <value>LCC110</value>
      <footprint>Package_DIP:DIP-8_W7.62mm</footprint>
      <datasheet>http://www.ixysic.com/home/pdfs.nsf/www/LCC110.pdf/$file/LCC110.pdf</datasheet>
      <fields>
        <field name="Part#">CLA106-ND</field>
        <field name="Vendor">digikey</field>
      </fields>
      <libsource lib="Relay_SolidState" part="LCC110" description="1-Form-C OptoMOS® Relay, DIP-8"/>
      <sheetpath names="/" tstamps="/"/>
      <tstamp>5E5D6E51</tstamp>
    </comp>
    <comp ref="R1">
      <value>220</value>
      <footprint>Resistor_THT:R_Axial_DIN0207_L6.3mm_D2.5mm_P7.62mm_Horizontal</footprint>
      <datasheet>~</datasheet>
      <libsource lib="Device" part="R_Small_US" description="Resistor, small US symbol"/>
      <sheetpath names="/" tstamps="/"/>
      <tstamp>5E5FAFCC</tstamp>
    </comp>
    <comp ref="D1">
      <value>D_Schottky_ALT</value>
      <footprint>Diode_THT:D_DO-41_SOD81_P7.62mm_Horizontal</footprint>
      <datasheet>http://www.vishay.com/docs/88525/1n5817.pdf</datasheet>
      <fields>
        <field name="Part#">1N5819-E3/54GICT-ND</field>
        <field name="Vendor">digikey</field>
      </fields>
      <libsource lib="Device" part="D_Schottky_ALT" description="Schottky diode, filled shape"/>
      <sheetpath names="/" tstamps="/"/>
      <tstamp>5E621824</tstamp>
    </comp>
    <comp ref="D2">
      <value>D_Schottky_ALT</value>
      <footprint>Diode_THT:D_DO-41_SOD81_P7.62mm_Horizontal</footprint>
      <datasheet>http://www.vishay.com/docs/88525/1n5817.pdf</datasheet>
      <fields>
        <field name="Part#">1N5819-E3/54GICT-ND</field>
        <field name="Vendor">digikey</field>
      </fields>
      <libsource lib="Device" part="D_Schottky_ALT" description="Schottky diode, filled shape"/>
      <sheetpath names="/" tstamps="/"/>
      <tstamp>5E621F90</tstamp>
    </comp>
    <comp ref="H1">
      <value>MountingHole_Pad</value>
      <footprint>MountingHole:MountingHole_3.5mm_Pad</footprint>
      <datasheet>~</datasheet>
      <libsource lib="Mechanical" part="MountingHole_Pad" description="Mounting Hole with connection"/>
      <sheetpath names="/" tstamps="/"/>
      <tstamp>5E7116D4</tstamp>
    </comp>
    <comp ref="R2">
      <value>10k</value>
      <footprint>Resistor_THT:R_Axial_DIN0207_L6.3mm_D2.5mm_P7.62mm_Horizontal</footprint>
      <datasheet>~</datasheet>
      <libsource lib="Device" part="R_Small_US" description="Resistor, small US symbol"/>
      <sheetpath names="/" tstamps="/"/>
      <tstamp>5E723C5A</tstamp>
    </comp>
    <comp ref="J2">
      <value>Screw_Terminal_01x06</value>
      <footprint>TerminalBlock_Phoenix:TerminalBlock_Phoenix_PT-1,5-6-5.0-H_1x06_P5.00mm_Horizontal</footprint>
      <datasheet>https://media.digikey.com/pdf/Data%20Sheets/Phoenix%20Contact%20PDFs/1935200.pdf</datasheet>
      <fields>
        <field name="Part#">277-1581-ND</field>
        <field name="Vendor">digikey</field>
      </fields>
      <libsource lib="Connector" part="Screw_Terminal_01x06" description="Generic screw terminal, single row, 01x06, script generated (kicad-library-utils/schlib/autogen/connector/)"/>
      <sheetpath names="/" tstamps="/"/>
      <tstamp>5E74116A</tstamp>
    </comp>
    <comp ref="C5">
      <value>470uF</value>
      <footprint>Capacitor_THT:CP_Radial_D8.0mm_P3.50mm</footprint>
      <datasheet>http://nichicon-us.com/english/products/pdfs/e-upw.pdf</datasheet>
      <fields>
        <field name="Part#">493-1702-ND</field>
        <field name="Vendor">digikey</field>
      </fields>
      <libsource lib="Device" part="CP" description="Polarized capacitor"/>
      <sheetpath names="/" tstamps="/"/>
      <tstamp>5E5FB13C</tstamp>
    </comp>
    <comp ref="C6">
      <value>470uF</value>
      <footprint>Capacitor_THT:CP_Radial_D8.0mm_P3.50mm</footprint>
      <datasheet>http://nichicon-us.com/english/products/pdfs/e-upw.pdf</datasheet>
      <fields>
        <field name="Part#">493-1702-ND</field>
        <field name="Vendor">digikey</field>
      </fields>
      <libsource lib="Device" part="CP" description="Polarized capacitor"/>
      <sheetpath names="/" tstamps="/"/>
      <tstamp>5E5FCDDF</tstamp>
    </comp>
    <comp ref="JP1">
      <value>SolderJumper_2_Open</value>
      <footprint>Jumper:SolderJumper-2_P1.3mm_Open_RoundedPad1.0x1.5mm</footprint>
      <datasheet>~</datasheet>
      <libsource lib="Jumper" part="SolderJumper_2_Open" description="Solder Jumper, 2-pole, open"/>
      <sheetpath names="/" tstamps="/"/>
      <tstamp>5E630257</tstamp>
    </comp>
    <comp ref="JP2">
      <value>SolderJumper_2_Open</value>
      <footprint>Jumper:SolderJumper-2_P1.3mm_Open_RoundedPad1.0x1.5mm</footprint>
      <datasheet>~</datasheet>
      <libsource lib="Jumper" part="SolderJumper_2_Open" description="Solder Jumper, 2-pole, open"/>
      <sheetpath names="/" tstamps="/"/>
      <tstamp>5E6323A4</tstamp>
    </comp>
  </components>
  <libparts>
    <libpart lib="Connector" part="DB15_Female_HighDensity">
      <description>15-pin female D-SUB connector, High density (3 columns), Triple Row, Generic, VGA-connector</description>
      <docs> ~</docs>
      <footprints>
        <fp>DSUB*Female*</fp>
      </footprints>
      <fields>
        <field name="Reference">J</field>
        <field name="Value">DB15_Female_HighDensity</field>
      </fields>
      <pins>
        <pin num="1" name="~" type="passive"/>
        <pin num="2" name="~" type="passive"/>
        <pin num="3" name="~" type="passive"/>
        <pin num="4" name="~" type="passive"/>
        <pin num="5" name="~" type="passive"/>
        <pin num="6" name="~" type="passive"/>
        <pin num="7" name="~" type="passive"/>
        <pin num="8" name="~" type="passive"/>
        <pin num="9" name="~" type="passive"/>
        <pin num="10" name="~" type="passive"/>
        <pin num="11" name="~" type="passive"/>
        <pin num="12" name="~" type="passive"/>
        <pin num="13" name="~" type="passive"/>
        <pin num="14" name="~" type="passive"/>
        <pin num="15" name="~" type="passive"/>
      </pins>
    </libpart>
    <libpart lib="Connector" part="Screw_Terminal_01x06">
      <description>Generic screw terminal, single row, 01x06, script generated (kicad-library-utils/schlib/autogen/connector/)</description>
      <docs>~</docs>
      <footprints>
        <fp>TerminalBlock*:*</fp>
      </footprints>
      <fields>
        <field name="Reference">J</field>
        <field name="Value">Screw_Terminal_01x06</field>
      </fields>
      <pins>
        <pin num="1" name="Pin_1" type="passive"/>
        <pin num="2" name="Pin_2" type="passive"/>
        <pin num="3" name="Pin_3" type="passive"/>
        <pin num="4" name="Pin_4" type="passive"/>
        <pin num="5" name="Pin_5" type="passive"/>
        <pin num="6" name="Pin_6" type="passive"/>
      </pins>
    </libpart>
    <libpart lib="Connector_Generic" part="Conn_02x10_Odd_Even">
      <description>Generic connector, double row, 02x10, odd/even pin numbering scheme (row 1 odd numbers, row 2 even numbers), script generated (kicad-library-utils/schlib/autogen/connector/)</description>
      <docs>~</docs>
      <footprints>
        <fp>Connector*:*_2x??_*</fp>
      </footprints>
      <fields>
        <field name="Reference">J</field>
        <field name="Value">Conn_02x10_Odd_Even</field>
      </fields>
      <pins>
        <pin num="1" name="Pin_1" type="passive"/>
        <pin num="2" name="Pin_2" type="passive"/>
        <pin num="3" name="Pin_3" type="passive"/>
        <pin num="4" name="Pin_4" type="passive"/>
        <pin num="5" name="Pin_5" type="passive"/>
        <pin num="6" name="Pin_6" type="passive"/>
        <pin num="7" name="Pin_7" type="passive"/>
        <pin num="8" name="Pin_8" type="passive"/>
        <pin num="9" name="Pin_9" type="passive"/>
        <pin num="10" name="Pin_10" type="passive"/>
        <pin num="11" name="Pin_11" type="passive"/>
        <pin num="12" name="Pin_12" type="passive"/>
        <pin num="13" name="Pin_13" type="passive"/>
        <pin num="14" name="Pin_14" type="passive"/>
        <pin num="15" name="Pin_15" type="passive"/>
        <pin num="16" name="Pin_16" type="passive"/>
        <pin num="17" name="Pin_17" type="passive"/>
        <pin num="18" name="Pin_18" type="passive"/>
        <pin num="19" name="Pin_19" type="passive"/>
        <pin num="20" name="Pin_20" type="passive"/>
      </pins>
    </libpart>
    <libpart lib="Device" part="C">
      <description>Unpolarized capacitor</description>
      <docs>~</docs>
      <footprints>
        <fp>C_*</fp>
      </footprints>
      <fields>
        <field name="Reference">C</field>
        <field name="Value">C</field>
      </fields>
      <pins>
        <pin num="1" name="~" type="passive"/>
        <pin num="2" name="~" type="passive"/>
      </pins>
    </libpart>
    <libpart lib="Device" part="CP">
      <description>Polarized capacitor</description>
      <docs>~</docs>
      <footprints>
        <fp>CP_*</fp>
      </footprints>
      <fields>
        <field name="Reference">C</field>
        <field name="Value">CP</field>
      </fields>
      <pins>
        <pin num="1" name="~" type="passive"/>
        <pin num="2" name="~" type="passive"/>
      </pins>
    </libpart>
    <libpart lib="Device" part="Crystal">
      <description>Two pin crystal</description>
      <docs>~</docs>
      <footprints>
        <fp>Crystal*</fp>
      </footprints>
      <fields>
        <field name="Reference">Y</field>
        <field name="Value">Crystal</field>
      </fields>
      <pins>
        <pin num="1" name="1" type="passive"/>
        <pin num="2" name="2" type="passive"/>
      </pins>
    </libpart>
    <libpart lib="Device" part="D_Schottky_ALT">
      <description>Schottky diode, filled shape</description>
      <docs>~</docs>
      <footprints>
        <fp>TO-???*</fp>
        <fp>*_Diode_*</fp>
        <fp>*SingleDiode*</fp>
        <fp>D_*</fp>
      </footprints>
      <fields>
        <field name="Reference">D</field>
        <field name="Value">D_Schottky_ALT</field>
      </fields>
      <pins>
        <pin num="1" name="K" type="passive"/>
        <pin num="2" name="A" type="passive"/>
      </pins>
    </libpart>
    <libpart lib="Device" part="R_Small_US">
      <description>Resistor, small US symbol</description>
      <docs>~</docs>
      <footprints>
        <fp>R_*</fp>
      </footprints>
      <fields>
        <field name="Reference">R</field>
        <field name="Value">R_Small_US</field>
      </fields>
      <pins>
        <pin num="1" name="~" type="passive"/>
        <pin num="2" name="~" type="passive"/>
      </pins>
    </libpart>
    <libpart lib="Jumper" part="SolderJumper_2_Open">
      <description>Solder Jumper, 2-pole, open</description>
      <docs>~</docs>
      <footprints>
        <fp>SolderJumper*Open*</fp>
      </footprints>
      <fields>
        <field name="Reference">JP</field>
        <field name="Value">SolderJumper_2_Open</field>
      </fields>
      <pins>
        <pin num="1" name="A" type="passive"/>
        <pin num="2" name="B" type="passive"/>
      </pins>
    </libpart>
    <libpart lib="MCU_Microchip_ATmega" part="ATmega48PV-10PU">
      <aliases>
        <alias>ATmega48P-20PU</alias>
        <alias>ATmega48A-PU</alias>
        <alias>ATmega48PA-PU</alias>
        <alias>ATmega88PV-10PU</alias>
        <alias>ATmega88P-20PU</alias>
        <alias>ATmega88A-PU</alias>
        <alias>ATmega88PA-PU</alias>
        <alias>ATmega168PV-10PU</alias>
        <alias>ATmega168P-20PU</alias>
        <alias>ATmega168A-PU</alias>
        <alias>ATmega168PA-PU</alias>
        <alias>ATmega328-PU</alias>
        <alias>ATmega328P-PU</alias>
      </aliases>
      <description>10MHz, 4kB Flash, 512B SRAM, 256B EEPROM, DIP-28</description>
      <docs>http://ww1.microchip.com/downloads/en/DeviceDoc/Atmel-8025-8-bit-AVR-Microcontroller-ATmega48P-88P-168P_Datasheet.pdf</docs>
      <footprints>
        <fp>DIP*W7.62mm*</fp>
      </footprints>
      <fields>
        <field name="Reference">U</field>
        <field name="Value">ATmega48PV-10PU</field>
        <field name="Footprint">Package_DIP:DIP-28_W7.62mm</field>
      </fields>
      <pins>
        <pin num="1" name="~RESET~/PC6" type="BiDi"/>
        <pin num="2" name="PD0" type="BiDi"/>
        <pin num="3" name="PD1" type="BiDi"/>
        <pin num="4" name="PD2" type="BiDi"/>
        <pin num="5" name="PD3" type="BiDi"/>
        <pin num="6" name="PD4" type="BiDi"/>
        <pin num="7" name="VCC" type="power_in"/>
        <pin num="8" name="GND" type="power_in"/>
        <pin num="9" name="XTAL1/PB6" type="BiDi"/>
        <pin num="10" name="XTAL2/PB7" type="BiDi"/>
        <pin num="11" name="PD5" type="BiDi"/>
        <pin num="12" name="PD6" type="BiDi"/>
        <pin num="13" name="PD7" type="BiDi"/>
        <pin num="14" name="PB0" type="BiDi"/>
        <pin num="15" name="PB1" type="BiDi"/>
        <pin num="16" name="PB2" type="BiDi"/>
        <pin num="17" name="PB3" type="BiDi"/>
        <pin num="18" name="PB4" type="BiDi"/>
        <pin num="19" name="PB5" type="BiDi"/>
        <pin num="20" name="AVCC" type="power_in"/>
        <pin num="21" name="AREF" type="passive"/>
        <pin num="22" name="GND" type="passive"/>
        <pin num="23" name="PC0" type="BiDi"/>
        <pin num="24" name="PC1" type="BiDi"/>
        <pin num="25" name="PC2" type="BiDi"/>
        <pin num="26" name="PC3" type="BiDi"/>
        <pin num="27" name="PC4" type="BiDi"/>
        <pin num="28" name="PC5" type="BiDi"/>
      </pins>
    </libpart>
    <libpart lib="Mechanical" part="MountingHole_Pad">
      <description>Mounting Hole with connection</description>
      <docs>~</docs>
      <footprints>
        <fp>MountingHole*Pad*</fp>
      </footprints>
      <fields>
        <field name="Reference">H</field>
        <field name="Value">MountingHole_Pad</field>
      </fields>
      <pins>
        <pin num="1" name="1" type="input"/>
      </pins>
    </libpart>
    <libpart lib="Relay_SolidState" part="LCC110">
      <description>1-Form-C OptoMOS® Relay, DIP-8</description>
      <docs>http://www.ixysic.com/home/pdfs.nsf/www/LCC110.pdf/$file/LCC110.pdf</docs>
      <footprints>
        <fp>DIP*W7.62mm*</fp>
      </footprints>
      <fields>
        <field name="Reference">U</field>
        <field name="Value">LCC110</field>
        <field name="Footprint">Package_DIP:DIP-8_W7.62mm</field>
      </fields>
      <pins>
        <pin num="1" name="nc" type="NotConnected"/>
        <pin num="2" name="~" type="passive"/>
        <pin num="3" name="~" type="passive"/>
        <pin num="4" name="nc" type="NotConnected"/>
        <pin num="5" name="~" type="passive"/>
        <pin num="6" name="~" type="passive"/>
        <pin num="7" name="~" type="passive"/>
        <pin num="8" name="~" type="passive"/>
      </pins>
    </libpart>
  </libparts>
  <libraries>
    <library logical="Connector">
      <uri>/usr/share/kicad/library/Connector.lib</uri>
    </library>
    <library logical="Connector_Generic">
      <uri>/usr/share/kicad/library/Connector_Generic.lib</uri>
    </library>
    <library logical="Device">
      <uri>/usr/share/kicad/library/Device.lib</uri>
    </library>
    <library logical="Jumper">
      <uri>/usr/share/kicad/library/Jumper.lib</uri>
    </library>
    <library logical="MCU_Microchip_ATmega">
      <uri>/usr/share/kicad/library/MCU_Microchip_ATmega.lib</uri>
    </library>
    <library logical="Mechanical">
      <uri>/usr/share/kicad/library/Mechanical.lib</uri>
    </library>
    <library logical="Relay_SolidState">
      <uri>/usr/share/kicad/library/Relay_SolidState.lib</uri>
    </library>
  </libraries>
  <nets>
    <net code="1" name="/LPIACT:L1_LP">
      <node ref="J2" pin="6"/>
      <node ref="U3" pin="6"/>
      <node ref="U3" pin="7"/>
      <node ref="J20" pin="12"/>
      <node ref="J20" pin="10"/>
    </net>
    <net code="2" name="/5V_TRICKLE">
      <node ref="D1" pin="2"/>
      <node ref="R2" pin="2"/>
      <node ref="C5" pin="1"/>
      <node ref="J20" pin="6"/>
      <node ref="U1" pin="20"/>
      <node ref="U1" pin="7"/>
      <node ref="U3" pin="5"/>
    </net>
    <net code="3" name="Net-(R1-Pad2)">
      <node ref="U3" pin="3"/>
      <node ref="R1" pin="2"/>
    </net>
    <net code="4" name="Net-(U1-Pad13)">
      <node ref="U3" pin="2"/>
      <node ref="U1" pin="13"/>
    </net>
    <net code="5" name="Net-(U3-Pad4)">
      <node ref="U3" pin="4"/>
    </net>
    <net code="6" name="Net-(U1-Pad3)">
      <node ref="U1" pin="3"/>
    </net>
    <net code="7" name="Net-(U1-Pad2)">
      <node ref="U1" pin="2"/>
    </net>
    <net code="8" name="Net-(U1-Pad1)">
      <node ref="U1" pin="1"/>
    </net>
    <net code="9" name="Net-(U1-Pad26)">
      <node ref="U1" pin="26"/>
    </net>
    <net code="10" name="Net-(U1-Pad25)">
      <node ref="U1" pin="25"/>
    </net>
    <net code="11" name="Net-(U1-Pad24)">
      <node ref="U1" pin="24"/>
    </net>
    <net code="12" name="Net-(U1-Pad23)">
      <node ref="U1" pin="23"/>
    </net>
    <net code="13" name="Net-(U1-Pad18)">
      <node ref="U1" pin="18"/>
    </net>
    <net code="14" name="Net-(U1-Pad17)">
      <node ref="U1" pin="17"/>
    </net>
    <net code="15" name="Net-(U1-Pad16)">
      <node ref="U1" pin="16"/>
    </net>
    <net code="16" name="Net-(U1-Pad15)">
      <node ref="U1" pin="15"/>
    </net>
    <net code="17" name="Net-(U1-Pad14)">
      <node ref="U1" pin="14"/>
    </net>
    <net code="18" name="Net-(U2-Pad14)">
      <node ref="U2" pin="14"/>
    </net>
    <net code="19" name="Net-(U2-Pad13)">
      <node ref="U2" pin="13"/>
    </net>
    <net code="20" name="Net-(U2-Pad12)">
      <node ref="U2" pin="12"/>
    </net>
    <net code="21" name="Net-(U2-Pad11)">
      <node ref="U2" pin="11"/>
    </net>
    <net code="22" name="Net-(C4-Pad1)">
      <node ref="U2" pin="10"/>
      <node ref="C4" pin="1"/>
      <node ref="Y2" pin="2"/>
    </net>
    <net code="23" name="Net-(U2-Pad1)">
      <node ref="U2" pin="1"/>
    </net>
    <net code="24" name="Net-(C3-Pad2)">
      <node ref="Y2" pin="1"/>
      <node ref="C3" pin="2"/>
      <node ref="U2" pin="9"/>
    </net>
    <net code="25" name="Net-(U2-Pad15)">
      <node ref="U2" pin="15"/>
    </net>
    <net code="26" name="GND">
      <node ref="J1" pin="5"/>
      <node ref="J1" pin="6"/>
      <node ref="J20" pin="18"/>
      <node ref="J1" pin="7"/>
      <node ref="J20" pin="16"/>
      <node ref="J1" pin="8"/>
      <node ref="J20" pin="14"/>
      <node ref="C3" pin="1"/>
      <node ref="R1" pin="1"/>
      <node ref="U1" pin="8"/>
      <node ref="U1" pin="22"/>
      <node ref="C4" pin="2"/>
      <node ref="C2" pin="2"/>
      <node ref="U3" pin="8"/>
      <node ref="J1" pin="10"/>
      <node ref="J20" pin="4"/>
      <node ref="J20" pin="3"/>
      <node ref="J20" pin="20"/>
      <node ref="H1" pin="1"/>
      <node ref="U2" pin="8"/>
      <node ref="U2" pin="22"/>
      <node ref="C6" pin="2"/>
      <node ref="C1" pin="1"/>
      <node ref="C5" pin="2"/>
    </net>
    <net code="27" name="Net-(U2-Pad26)">
      <node ref="U2" pin="26"/>
    </net>
    <net code="28" name="Net-(U3-Pad1)">
      <node ref="U3" pin="1"/>
    </net>
    <net code="29" name="Net-(U2-Pad6)">
      <node ref="U2" pin="6"/>
    </net>
    <net code="30" name="Net-(U2-Pad5)">
      <node ref="U2" pin="5"/>
    </net>
    <net code="31" name="Net-(U2-Pad4)">
      <node ref="U2" pin="4"/>
    </net>
    <net code="32" name="Net-(U2-Pad3)">
      <node ref="U2" pin="3"/>
    </net>
    <net code="33" name="Net-(U1-Pad4)">
      <node ref="U1" pin="4"/>
    </net>
    <net code="34" name="Net-(U2-Pad25)">
      <node ref="U2" pin="25"/>
    </net>
    <net code="35" name="Net-(U2-Pad24)">
      <node ref="U2" pin="24"/>
    </net>
    <net code="36" name="Net-(U2-Pad23)">
      <node ref="U2" pin="23"/>
    </net>
    <net code="37" name="Net-(U2-Pad21)">
      <node ref="U2" pin="21"/>
    </net>
    <net code="38" name="Net-(U2-Pad2)">
      <node ref="U2" pin="2"/>
    </net>
    <net code="39" name="Net-(U2-Pad19)">
      <node ref="U2" pin="19"/>
    </net>
    <net code="40" name="Net-(U2-Pad18)">
      <node ref="U2" pin="18"/>
    </net>
    <net code="41" name="Net-(U2-Pad17)">
      <node ref="U2" pin="17"/>
    </net>
    <net code="42" name="Net-(U2-Pad16)">
      <node ref="U2" pin="16"/>
    </net>
    <net code="43" name="/PWR_BTN">
      <node ref="R2" pin="1"/>
      <node ref="U1" pin="19"/>
      <node ref="J2" pin="1"/>
    </net>
    <net code="44" name="/PROT">
      <node ref="J20" pin="7"/>
      <node ref="J2" pin="4"/>
    </net>
    <net code="45" name="/COMPUTER_5V">
      <node ref="D2" pin="2"/>
      <node ref="J1" pin="9"/>
      <node ref="C6" pin="1"/>
    </net>
    <net code="46" name="Net-(D1-Pad1)">
      <node ref="D2" pin="1"/>
      <node ref="U2" pin="20"/>
      <node ref="U2" pin="7"/>
      <node ref="D1" pin="1"/>
    </net>
    <net code="47" name="Net-(U1-Pad12)">
      <node ref="U1" pin="12"/>
    </net>
    <net code="48" name="Net-(U1-Pad11)">
      <node ref="U1" pin="11"/>
    </net>
    <net code="49" name="Net-(U1-Pad6)">
      <node ref="U1" pin="6"/>
    </net>
    <net code="50" name="Net-(U1-Pad5)">
      <node ref="U1" pin="5"/>
    </net>
    <net code="51" name="/DCO">
      <node ref="J2" pin="5"/>
      <node ref="J20" pin="5"/>
    </net>
    <net code="52" name="/-10V">
      <node ref="J20" pin="8"/>
      <node ref="J2" pin="3"/>
    </net>
    <net code="53" name="/LINE_SENSE">
      <node ref="J20" pin="19"/>
      <node ref="J2" pin="2"/>
    </net>
    <net code="54" name="/IVAD_SCL">
      <node ref="J20" pin="2"/>
      <node ref="U1" pin="28"/>
    </net>
    <net code="55" name="/IVAD_SDA">
      <node ref="J20" pin="1"/>
      <node ref="U1" pin="27"/>
    </net>
    <net code="56" name="Net-(U1-Pad21)">
      <node ref="U1" pin="21"/>
    </net>
    <net code="57" name="Net-(C2-Pad1)">
      <node ref="C2" pin="1"/>
      <node ref="Y1" pin="2"/>
      <node ref="U1" pin="10"/>
    </net>
    <net code="58" name="Net-(C1-Pad2)">
      <node ref="C1" pin="2"/>
      <node ref="Y1" pin="1"/>
      <node ref="U1" pin="9"/>
    </net>
    <net code="59" name="Net-(J1-Pad15)">
      <node ref="JP2" pin="1"/>
      <node ref="J1" pin="15"/>
    </net>
    <net code="60" name="Net-(J1-Pad4)">
      <node ref="J1" pin="4"/>
    </net>
    <net code="61" name="Net-(J1-Pad12)">
      <node ref="JP1" pin="1"/>
      <node ref="J1" pin="12"/>
    </net>
    <net code="62" name="Net-(J1-Pad11)">
      <node ref="J1" pin="11"/>
    </net>
    <net code="63" name="/RED">
      <node ref="J20" pin="17"/>
      <node ref="J1" pin="1"/>
    </net>
    <net code="64" name="/GREEN">
      <node ref="J1" pin="2"/>
      <node ref="J20" pin="15"/>
    </net>
    <net code="65" name="/COMPUTER_SDA">
      <node ref="U2" pin="27"/>
      <node ref="JP1" pin="2"/>
    </net>
    <net code="66" name="/COMPUTER_SCL">
      <node ref="JP2" pin="2"/>
      <node ref="U2" pin="28"/>
    </net>
    <net code="67" name="/BLUE">
      <node ref="J1" pin="3"/>
      <node ref="J20" pin="13"/>
    </net>
    <net code="68" name="/V_SYNC">
      <node ref="J1" pin="14"/>
      <node ref="J20" pin="11"/>
    </net>
    <net code="69" name="/H_SYNC">
      <node ref="J1" pin="13"/>
      <node ref="J20" pin="9"/>
    </net>
  </nets>
</export>
